{
  "leader": {
    "Logical record length": [
      0,
      4
    ],
    "Record status": [
      5,
      {
        "Increase in encoding level": "a",
        "Corrected or revised": "c",
        "Deleted": "d",
        "New": "n",
        "Increase in encoding level from prepublication": "p"
      }
    ],
    "Type of Record": [
      6,
      {
        "Language material": "a",
        "Archival and manuscripts control [OBSOLETE]": "b",
        "Notated music": "c",
        "Manuscript notated music": "d",
        "Cartographic material": "e",
        "Manuscript cartographic material": "f",
        "Projected medium": "g",
        "Microform publications [OBSOLETE]": "h",
        "Nonmusical sound recording": "i",
        "Musical sound recording": "j",
        "Two-dimensional nonprojectable graphic": "k",
        "Computer file": "m",
        "Special instructional material [OBSOLETE]": "n",
        "Kit": "o",
        "Mixed material": "p",
        "Three-dimensional artifact or naturally occurring object": "r",
        "Manuscript language material": "t"
      }
    ],
    "Bibliographic level": [
      7,
      {
        "Monographic component part": "a",
        "Serial component part": "b",
        "Collection": "c",
        "Subunit": "d",
        "Integrating resource": "i",
        "Monograph/item": "m",
        "Serial": "s"
      }
    ],
    "Type of Control": [
      8,
      {
        "No specific type": "#",
        "Archival": "a"
      }
    ],
    "Character coding scheme": [
      9,
      {
        "MARC-8": "#",
        "UCS/Unicode": "a"
      }
    ],
    "Indicator count": 10,
    "Subfield code count": 11,
    "Base address of data": [
      12,
      16
    ],
    "Encoding level": [
      17,
      {
        "Full level": "#",
        "Full level, material not examined": "1",
        "Less-than-full level, material not examined": "2",
        "Abbreviated level": "3",
        "Core level": "4",
        "Partial (preliminary) level": "5",
        "Minimal level": "7",
        "Prepublication level": "8",
        "Unknown": "u",
        "Not applicable": "z"
      }
    ],
    "Descriptive cataloging form": [
      18,
      {
        "Non-ISBD": "#",
        "AACR 2": "a",
        "ISBD punctuation omitted": "c",
        "ISBD punctuation included": "i",
        "Non-ISBD punctuation omitted": "n",
        "Partial ISBD (BK) [OBSOLETE]": "p",
        "Provisional (VM MP MU) [OBSOLETE]": "r",
        "Unknown": "u"
      }
    ],
    "Multipart resource record level": [
      19,
      {
        "Not specified or not applicable": "#",
        "Set": "a",
        "Part with independent title": "b",
        "Part with dependent title": "c"
      }
    ],
    "Entry Map": [
      20,
      23,
      [
        "Length of the length-of-field portion",
        "Length of the starting-character-position portion",
        "Length of the implementation-defined portion",
        "Undefined Entry map character position"
      ]
    ]
  },
  "directory": {
    "tag": [
      0,
      2
    ],
    "Field length": [
      3,
      6
    ],
    "Starting character position": [
      7,
      11
    ]
  },
  "controlfield": {
    "CONTROL NUMBER": "001",
    "CONTROL NUMBER IDENTIFIER": "003",
    "DATE AND TIME OF LATEST TRANSACTION": "005",
    "ADDITIONAL MATERIAL CHARACTERISTICS": [
      "006",
      {
        "Form of material$Books": [
          0,
          {
            "Language material": "a",
            "Manuscript language material": "t"
          }
        ],
        "Form of material$Computer Files/Electronic resource": [
          0,
          {
            "Computer file/Electronic resource": "m"
          }
        ],
        "Form of material$Maps": [
          0,
          {
            "Cartographic material": "e",
            "Manuscript cartographic material": "f"
          }
        ],
        "Form of material$MIXED MATERIALS": [
          0,
          {
            "Mixed material": "p"
          }
        ],
        "Form of material$MUSIC": [
          0,
          {
            "Notated music": "c",
            "Manuscript notated music": "d",
            "Nonmusical sound recording": "i",
            "Musical sound recording": "j"
          }
        ],
        "Form of material$CONTINUING RESOURCES": [
          0,
          {
            "Serial/Integrating resource": "s"
          }
        ],
        "Form of material$VISUAL MATERIALS": [
          0,
          {
            "Projected medium": "g",
            "Two-dimensional nonprojectable graphic": " k",
            "Kit": "o",
            "Three-dimensional artifact or naturally occurring object": "r"
          }
        ],
        "$Books": {
          "Illustrations": [
            1,
            4
          ],
          "Nature of contents": [
            7,
            10
          ],
          "Conference publication": 12,
          "Festschrift": 13,
          "Index": 14,
          "Literary form": 16,
          "Biography": 17
        },
        "$Computer Files/Electronic resource": {
          "Type of computer file": 9
        },
        "$Maps": {
          "Relief": [
            1,
            4
          ],
          "Projection": [
            5,
            6
          ],
          "Prime meridian [OBSOLETE]": 7,
          "Type of cartographic material": 8,
          "Index": 14,
          "Special format characteristics": [
            16,
            17
          ]
        },
        "$MUSIC": {
          "Form of composition": [
            1,
            2
          ],
          "Format of music": 3,
          "Music parts": 4,
          "Accompanying matter": [
            7,
            12
          ],
          "Literary text for sound recordings": [
            13,
            14
          ],
          "Transposition and arrangement": 16
        },
        "$CONTINUING RESOURCES": {
          "Frequency": 1,
          "Regularity": 2,
          "ISSN Center [OBSOLETE]": 3,
          "Type of continuing resource": 4,
          "Form of original item": 5,
          "Nature of entire work": 7,
          "Nature of contents": [
            8,
            10
          ],
          "Conference publication": 12,
          "Original alphabet or script of title": 16,
          "Entry convention": 17
        },
        "$VISUAL MATERIALS": {
          "Accompanying matter [OBSOLETE]": [
            6,
            10
          ],
          "Type of visual material": 16,
          "Technique": 17
        },
        "Target audience": 5,
        "Form of item": 6,
        "Government publication": 11
      }
    ],
    "PHYSICAL DESCRIPTION": [
      "007",
      {
        "Category of material$Map": [
          0,
          {
            "Map": "a"
          }
        ],
        "Category of material$ELECTRONIC RESOURCE": [
          0,
          {
            "Computer file": "c"
          }
        ],
        "Category of material$GLOBE": [
          0,
          {
            "Globe": "d"
          }
        ],
        "Category of material$TACTILE MATERIAL": [
          0,
          {
            "Tactile material": "f"
          }
        ],
        "Category of material$PROJECTED GRAPHIC": [
          0,
          {
            "Projected graphic": "g"
          }
        ],
        "Category of material$MICROFORM": [
          0,
          {
            "Microform": "h"
          }
        ],
        "Category of material$NONPROJECTED GRAPHIC": [
          0,
          {
            "Nonprojected graphic": "k"
          }
        ],
        "Category of material$MOTION PICTURE": [
          0,
          {
            "Motion Picture": "m"
          }
        ],
        "Category of material$KIT": [
          0,
          {
            "Kit": "o"
          }
        ],
        "Category of material$NOTATED MUSIC": [
          0,
          {
            "Notated music": "q"
          }
        ],
        "Category of material$SOUND RECORDING": [
          0,
          {
            "Sound recording": "s"
          }
        ],
        "Category of material$REMOTE-SENSING IMAGE": [
          0,
          {
            "Remote-sensing image": "r"
          }
        ],
        "Category of material$TEXT": [
          0,
          {
            "Text": "t"
          }
        ],
        "Category of material$VIDEORECORDING": [
          0,
          {
            "Videorecording": "v"
          }
        ],
        "Category of material$UNSPECIFIED": [
          0,
          {
            "Unspecified": "z"
          }
        ],
        "$Map": {
          "Specific material designation": [
            1,
            {
              "Atlas": "d",
              "Diagram": "g",
              "Map": "j",
              "Profile": "k",
              "Model": "q",
              "Remote-sensing image": "r",
              "Section": "s",
              "Unspecified": "u",
              "View": "y"
            }
          ],
          "Color": [
            3,
            {
              "One color": "a",
              "Multicolored": "c"
            }
          ],
          "Physical medium": [
            4,
            {
              "Paper": "a",
              "Wood": "b",
              "Stone": "c",
              "Metal": "d",
              "Synthetic": "e",
              "Skin": "f",
              "Textile": "g",
              "Plastic": "i",
              "Glass": "j",
              "Vinyl": "l",
              "Vellum": "n",
              "Plaster": "p",
              "Flexible base photographic, positive": "q",
              "Flexible base photographic, negative": "r",
              "Non-flexible base photographic, positive": "s",
              "Non-flexible base photographic, negative": "t",
              "Unknown": "u",
              "Leather": "v",
              "Parchment": "w",
              "Other photographic medium": "y"
            }
          ],
          "Type of reproduction": [
            5,
            {
              "Facsimile": "f"
            }
          ],
          "Production/reproduction details": [
            6,
            {
              "Photocopy, blueline print": "a",
              "Photocopy": "b",
              "Pre-production": "c",
              "Film": "d"
            }
          ],
          "Positive/negative aspect": [
            7,
            {
              "Positive": "a",
              "Negative": "b",
              "Mixed polarity": "m",
              "Not applicable": "n"
            }
          ]
        },
        "$ELECTRONIC RESOURCE": {
          "Specific material designation": [
            1,
            {
              "Tape cartridge": "a",
              "Chip cartridge": "b",
              "Computer optical disc cartridge": "c",
              "Computer disc, type unspecified": "d",
              "Computer disc cartridge, type unspecified": "e",
              "Tape cassette": "f",
              "Tape reel": "h",
              "Magnetic disk": "j",
              "Computer card": "k",
              "Magneto-optical disc": "m",
              "Optical disc": "o",
              "Remote": "r",
              "Standalone device": "s",
              "Unspecified": "u"
            }
          ],
          "Color": [
            3,
            {
              "One color": "a",
              "Black-and-white": "b",
              "Multicolored": "c",
              "Gray scale": "g",
              "Mixed": "m"
            }
          ],
          "Dimensions": [
            4,
            {
              "3 1/2 in.": "a",
              "12 in.": "e",
              "4 3/4 in. or 12 cm.": "g",
              "1 1/8 x 2 3/8 in.": "i",
              "3 7/8 x 2 1/2 in.": "j",
              "5 1/4 in.": "o",
              "8 in.": "v"
            }
          ],
          "Sound": [
            5,
            {
              "No sound (silent)": "#",
              "Sound on medium": "a"
            }
          ],
          "Image bit depth": [
            6,
            8,
            {
              "Exact bit depth": [
                1,
                999
              ],
              "Multiple": "mmm",
              "Not applicable": "nnn",
              "Unknown": "---",
              "No attempt to code": "|||"
            }
          ],
          "File Formats": [
            9,
            {
              "One": "a",
              "Multiple": "m"
            }
          ],
          "Quality assurance target(s)": [
            10,
            {
              "Absent": "a",
              "Present": "p"
            }
          ],
          "Antecedent/source": [
            11,
            {
              "File reproduced from original": "a",
              "File reproduced from microform": "b",
              "File reproduced from an electronic resource": "c",
              "File reproduced from an intermediate (not microform)": "d"
            }
          ],
          "Level of compression": [
            12,
            {
              "Uncompressed": "a",
              "Lossless": "b",
              "Lossy": "d"
            }
          ],
          "Reformatting quality": [
            13,
            {
              "Access": "a",
              "Preservation": "p",
              "Replacement": "r"
            }
          ]
        },
        "$GLOBE": {
          "Specific material designation": [
            1,
            {
              "Celestial globe": "a",
              "Planetary or lunar globe": "b",
              "Terrestrial globe": "c",
              "Earth moon globe": "e",
              "Unspecified": "u"
            }
          ],
          "Color": [
            3,
            {
              "One color": "a",
              "Multicolored": "c"
            }
          ],
          "Physical medium": [
            4,
            {
              "Paper": "a",
              "Wood": "b",
              "Stone": "c",
              "Metal": "d",
              "Synthetic": "e",
              "Skin": "f",
              "Textile": "g",
              "Plastic": "i",
              "Vinyl": "l",
              "Vellum": "n",
              "Plaster": "p",
              "Leather": "v",
              "Parchment": "w"
            }
          ],
          "Type of reproduction": [
            5,
            {
              "Facsimile": "f"
            }
          ]
        },
        "$TACTILE MATERIAL": {
          "Specific material designation": [
            1,
            {
              "Moon": "a",
              "Braille": "b",
              "Combination": "c",
              "Tactile, with no writing system": "d"
            }
          ],
          "Class of braille writing": [
            3,
            4,
            {
              "No specified class of braille writing": "#",
              "Literary braille": "a",
              "Format code braille": "b",
              "Mathematics and scientific braille": "c",
              "Computer braille": "d",
              "Music braille": "e",
              "Multiple braille types": "m"
            }
          ],
          "Level of contraction": [
            5,
            {
              "Uncontracted": "a",
              "Contracted": "b"
            }
          ],
          "Braille music format": [
            6,
            8,
            {
              "No specified braille music format": "#",
              "Bar over bar": "a",
              "Bar by bar": "b",
              "Line over line": "c",
              "Paragraph": "d",
              "Single line": "e",
              "Section by section": "f",
              "Line by line": "g",
              "Open score": "h",
              "Spanner short form scoring": "i",
              "Short form scoring": "j",
              "Outline": "k",
              "Vertical score": "l"
            }
          ],
          "Specific physical characteristics": [
            9,
            {
              "Print/braille": "a",
              "Jumbo or enlarged braille": "b"
            }
          ]
        },
        "$PROJECTED GRAPHIC": {
          "Specific material designation": [
            1,
            {
              "Filmstrip cartridge": "c",
              "Filmslip": "d",
              "Filmstrip, type unspecified": "f",
              "Filmstrip roll": "o",
              "Slide": "s",
              "Transparency": "t"
            }
          ],
          "Color": [
            3,
            {
              "One color": "a",
              "Black-and-white": "b",
              "Multicolored": "c",
              "Hand colored": "h"
            }
          ],
          "Base of emulsion": [
            4,
            {
              "Glass": "d",
              "Synthetic": "e",
              "Safety film": "j",
              "Film base, other than safety film": "k",
              "Mixed collection": "m",
              "Paper": "o"
            }
          ],
          "Sound on medium or separate": [
            5,
            {
              "No sound (silent)": "#",
              "Sound on medium": "a",
              "Sound separate from medium": "b"
            }
          ],
          "Medium for sound": [
            6,
            {
              "No sound (silent)": "#",
              "Optical sound track on motion picture film": "a",
              "Magnetic sound track on motion picture film": "b",
              "Magnetic audio tape in cartridge": "c",
              "Sound disc": "d",
              "Magnetic audio tape on reel": "e",
              "Magnetic audio tape in cassette": "f",
              "Optical and magnetic sound track on motion picture film": "g",
              "Videotape": "h",
              "Videodisc": "i"
            }
          ],
          "Dimensions": [
            7,
            {
              "Standard 8 mm.": "a",
              "Super 8 mm./single 8 mm.": "b",
              "9.5 mm.": "c",
              "16 mm.": "d",
              "28 mm.": "e",
              "35 mm.": "f",
              "70 mm.": "g",
              "2x2 in. or 5x5 cm.": "j",
              "2 1/4 x 2 1/4 in. or 6x6 cm.": "k",
              "4x5 in. or 10x13 cm.": "s",
              "5x7 in. or 13x18 cm.": "t",
              "8x10 in. or 21x26 cm.": "v",
              "9x9 in. or 23x23 cm.": "w",
              "10x10 in. or 26x26 cm.": "x",
              "7x7 in. or 18x18 cm.": "y"
            }
          ],
          "Secondary support material": [
            8,
            {
              "No secondary support": "#",
              "Cardboard": "c",
              "Glass": "d",
              "Synthetic": "e",
              "Metal": "h",
              "Metal and glass": "j",
              "Synthetic and glass": "k",
              "Mixed collection": "m"
            }
          ]
        },
        "$MICROFORM": {
          "Specific material designation": [
            1,
            {
              "Aperture card": "a",
              "Microfilm cartridge": "b",
              "Microfilm cassette": "c",
              "Microfilm reel": "d",
              "Microfiche": "e",
              "Microfiche cassette": "f",
              "Microopaque": "g",
              "Microfilm slip": "h",
              "Micrcrofilm roll": "j"
            }
          ],
          "Positive/negative aspect": [
            3,
            {
              "Positive": "a",
              "Negative": "b",
              "Mixed polarity": "m"
            }
          ],
          "Dimensions": [
            4,
            {
              "8 mm.": "a",
              "16 mm.": "d",
              "35 mm.": "f",
              "70 mm.": "g",
              "105 mm.": "h",
              "3x5 in. or 8x13 cm.": "l",
              "4x6 in. or 11x15 cm.": "m",
              "6x9 in. or 16x23 cm.": "o",
              "3 1/4 x 7 3/8 in. or 9x19 cm.": "p"
            }
          ],
          "Reduction ratio range": [
            5,
            {
              "Low reduction": "a",
              "Normal reduction": "b",
              "High reduction": "c",
              "Very high reduction": "d",
              "Ultra high reduction": "e",
              "Reduction rate varies": "v"
            }
          ],
          "Reduction ratio": [
            6,
            8
          ],
          "Color": [
            9,
            {
              "Black-and-white (or monochrome)": "b",
              "Multicolored": "c"
            }
          ],
          "Emulsion on film": [
            10,
            {
              "Silver halide": "a",
              "Diazo": "b",
              "Vesicular": "c",
              "Mixd emulsion": "m"
            }
          ],
          "Generation": [
            11,
            {
              "First generation (master)": "a",
              "Printing master": "b",
              "Service copy": "c",
              "Mixed generation": "m"
            }
          ],
          "Base of film": [
            12,
            {
              "Safety base, undetermined": "a",
              "Safety base, acetate undetermined": "c",
              "Safety base, diacetate": "d",
              "Safety base, polyester": "p",
              "Safety base, mixed": "r",
              "Safety base, triacetate": "t",
              "Nitrate base": "i",
              "Mixed base (nitrate and safety)": "m"
            }
          ]
        },
        "$NONPROJECTED GRAPHIC": {
          "Specific material designation": [
            1,
            {
              "Activity Card": "a",
              "Collage": "c",
              "Drawing": "d",
              "Painting": "e",
              "Photomechanical print": "f",
              "Photonegative": "g",
              "Photoprint": "h",
              "Picture": "i",
              "Print": "j",
              "Poster": "k",
              "Technical drawing": "l",
              "Chart": "n",
              "Flash card": "o",
              "Postcard": "p",
              "Icon": "q",
              "Radiograph": "r",
              "Study print": "s",
              "Photograph, type unspecified": "v"
            }
          ],
          "Color": [
            3,
            {
              "One color": "a",
              "Black-and-white": "b",
              "Multicolored": "c",
              "Hand colored": "h"
            }
          ],
          "Primary support material": [
            4,
            {
              "Canvas": "a",
              "Bristol board": "b",
              "Cardboard/illustration board": "c",
              "Glass": "d",
              "Synthetic": "e",
              "Skin": "f",
              "Textile": "g",
              "Metal": "h",
              "Plastic": "i",
              "Vinyl": "l",
              "Mixed collection": "m",
              "Vellum": "n",
              "Paper": "o",
              "Plaster": "p",
              "Hardboard": "q",
              "Porcelain": "r",
              "Stone": "s",
              "Wood": "t",
              "Leather": "v",
              "Parchment": "w"
            }
          ],
          "Secondary support material": [
            5,
            {
              "No secondary support": "#",
              "Canvas": "a",
              "Bristol board": "b",
              "Cardboard/illustration board": "c",
              "Glass": "d",
              "Synthetic": "e",
              "Skin": "f",
              "Textile": "g",
              "Metal": "h",
              "Plastic": "i",
              "Vinyl": "l",
              "Mixed collection": "m",
              "Vellum": "n",
              "Paper": "o",
              "Plaster": "p",
              "Hardboard": "q",
              "Porcelain": "r",
              "Stone": "s",
              "Wood": "t",
              "Leather": "v",
              "Parchment": "w"
            }
          ]
        },
        "$MOTION PICTURE": {
          "Specific material designation": [
            1,
            {
              "Film cartridge": "c",
              "Film cassette": "f",
              "Film roll": "o",
              "Film reel": "r"
            }
          ],
          "Color": [
            3,
            {
              "Black-and-white": "b",
              "Multicolored": "c",
              "Hand colored": "h"
            }
          ],
          "Motion picture presentation format": [
            4,
            {
              "Standard sound aperture (reduced frame)": "a",
              "Nonanamorphic (wide-screen)": "b",
              "3D": "c",
              "Anamorphic (wide-screen)": "d",
              "Other wide-screen format": "e",
              "Standard silent aperture (full frame)": "f"
            }
          ],
          "Sound on medium or separate": [
            5,
            {
              "No sound (silent)": "#",
              "Sound on medium": "a",
              "Sound separate from medium": "b"
            }
          ],
          "Medium for sound": [
            6,
            {
              "No sound (silent)": "#",
              "Optical sound track on motion picture film": "a",
              "Magnetic sound track on motion picture film": "b",
              "Magnetic audio tape in cartridge": "c",
              "Sound disc": "d",
              "Magnetic audio tape on reel": "e",
              "Magnetic audio tape in cassette": "f",
              "Optical and magnetic sound track on motion picture film": "g",
              "Video tape": "h",
              "Videodisc": "i"
            }
          ],
          "Dimensions": [
            7,
            {
              "Standard 8 mm.": "a",
              "Super 8 mm./single 8 mm.": "b",
              "9.5 mm.": "c",
              "16 mm.": "d",
              "28 mm.": "e",
              "35 mm.": "f",
              "70 mm.": "g"
            }
          ],
          "Configuration of playback channels": [
            8,
            {
              "Mixed": "k",
              "Monaural": "m",
              "Not applicable": "n",
              "Quadraphonic, multichannel, or surround": "q",
              "Stereophonic": "s"
            }
          ],
          "Production elements": [
            9,
            {
              "Workprint": "a",
              "Trims": "b",
              "Outtakes": "c",
              "Rushes": "d",
              "Mixing tracks": "e",
              "Title bands/intertitle rolls": "f",
              "Production rolls": "g"
            }
          ],
          "Positive/negative aspect": [
            10,
            {
              "Positive": "a",
              "Negative": "b"
            }
          ],
          "Generation": [
            11,
            {
              "Duplicate": "d",
              "Master": "e",
              "Original": "o",
              "Reference print/viewing copy": "r",
              "Unknown": "u",
              "Other": "z",
              "No attempt to code": "|"
            }
          ],
          "Base of film": [
            12,
            {
              "Safety base, undetermined": "a",
              "Safety base, acetate undetermined": "c",
              "Safety base, diacetate": "d",
              "Safety base, polyester": "p",
              "Safety base, mixed": "r",
              "Safety base, triacetate": "t",
              "Nitrate base": "i",
              "Mixed base (nitrate and safety)": "m",
              "Not applicable": "n",
              "Unknown": "u",
              "Other": "z",
              "No attempt to code": "|"
            }
          ],
          "Refined categories of color": [
            13,
            {
              "3 layer color": "a",
              "2 color, single strip": "b",
              "Undetermined 2 color": "c",
              "Undetermined 3 color": "d",
              "3 strip color": "e",
              "2 strip color": "f",
              "Red strip": "g",
              "Blue or green strip": "h",
              "Cyan strip": "i",
              "Magenta strip": "j",
              "Yellow strip": "k",
              "S E N 2": "l",
              "S E N 3": "m",
              "Not applicable": "n",
              "Sepia tone": "p",
              "Other tone": "q",
              "Tint": "r",
              "Tinted and toned": "s",
              "Stencil color": "t",
              "Unknown": "u",
              "Hand colored": "v",
              "Other": "z",
              "No attempt to code": "|"
            }
          ],
          "Kind of color stock or print": [
            14,
            {
              "Imbibition dye transfer prints": "a",
              "Three layer stock": "b",
              "Three layer stock, low fade": "c",
              "Duplitized stock": "d",
              "Not applicable": "n",
              "Unknown": "u",
              "Other": "z",
              "No attempt to code": "|"
            }
          ],
          "Deterioration stage": [
            15,
            {
              "None apparent": "a",
              "Nitrate: suspicious odor": "b",
              "Nitrate: pungent odor": "c",
              "Nitrate: brownish, discoloration, fading, dusty": "d",
              "Nitrate: sticky": "e",
              "Nitrate: frothy, bubbles, blisters": "f",
              "Nitrate: congealed": "g",
              "Nitrate: powder": "h",
              "Non-nitrate: detectable deterioration (diacetate odor)": "k",
              "Non-nitrate: advanced deterioration": "l",
              "Non-nitrate: disaster": "m",
              "No attempt to code": "|"
            }
          ],
          "Completeness": [
            16,
            {
              "Complete": "c",
              "Incomplete": "i",
              "Not applicable": "n",
              "Unknown": "u",
              "No attempt to code": "|"
            }
          ],
          "Film inspection date": [
            17,
            22
          ]
        },
        "$KIT": {
          "Specific material designation": [
            1,
            {
              "Unspecified": "u"
            }
          ]
        },
        "$NOTATED MUSIC": {
          "Specific material designation": [
            1,
            {
              "Unspecified": "u"
            }
          ]
        },
        "$REMOTE-SENSING IMAGE": {
          "Specific material designation": [
            1,
            {
              "Unspecified": "u"
            }
          ],
          "Altitude of sensor": [
            3,
            {
              "Surface": "a",
              "Airborne": "b",
              "Spaceborne": "c",
              "Not applicable": "n",
              "Unknown": "u",
              "Other": "z",
              "No attempt to code": "|"
            }
          ],
          "Attitude of sensor": [
            4,
            {
              "Low oblique": "a",
              "High oblique": "b",
              "Vertical": "c",
              "Not applicable": "n",
              "Unknown": "u",
              "No attempt to code": "|"
            }
          ],
          "Cloud cover": [
            5,
            {
              "0-9%": 0,
              "10-19%": 1,
              "20-29%": 2,
              "30-39%": 3,
              "40-49%": 4,
              "50-59%": 5,
              "60-69%": 6,
              "70-79%": 7,
              "80-89%": 8,
              "90-100%": 9,
              "Not applicable": "n",
              "Unknown": "u",
              "No attempt to code": "|"
            }
          ],
          "Platform construction type": [
            6,
            {
              "Balloon": "a",
              "Aircraft--low altitude": "b",
              "Aircraft--medium altitude": "c",
              "Aircraft--high altitude": "d",
              "Manned spacecraft": "e",
              "Unmanned spacecraft": "f",
              "Land-based remote-sensing device": "g",
              "Water surface-based remote-sensing device": "h",
              "Submersible remote-sensing device": "i",
              "Not applicable": "n",
              "Unknown": "u",
              "Other": "z",
              "No attempt to code": "|"
            }
          ],
          "Platform use category": [
            7,
            {
              "Meteorological": "a",
              "Surface observing": "b",
              "Space observing": "c",
              "Mixed uses": "m",
              "Not applicable": "n",
              "Unknown": "u",
              "Other": "z",
              "No attempt to code": "|"
            }
          ],
          "Sensor type": [
            8,
            {
              "Active": "a",
              "Passive": "b",
              "Unknown": "u",
              "Other": "z",
              "No attempt to code": "|"
            }
          ],
          "Data type": [
            9,
            {
              "Visible light": "aa",
              "Near infrared": "da",
              "Middle infrared": "db",
              "Far infrared": "dc",
              "Thermal infrared": "dd",
              "Shortwave infrared (SWIR)": "de",
              "Reflective infrared": "df",
              "Combinations": "dv",
              "Other infrared data": "dz",
              "Sidelooking airborne radar (SLAR)": "ga",
              "Synthetic aperture radar (SAR)-Single frequency": "gb",
              "SAR-multi-frequency (multichannel)": "gc",
              "SAR-like polarization": "gd",
              "SAR-cross polarization": "ge",
              "Infometric SAR": "gf",
              "polarmetric SAR": "gg",
              "Passive microwave mapping": "gu",
              "Other microwave data": "gz",
              "Far ultraviolet": "ja",
              "Middle ultraviolet": "jb",
              "Near ultraviolet": "jc",
              "Ultraviolet combinations": "jv",
              "Other ultraviolet data": "jz",
              "Multi-spectral, multidata": "ma",
              "Multi-temporal": "mb",
              "Combination of various data types": "mm",
              "Not applicable": "nn",
              "Sonar--water depth": "pa",
              "Sonar--bottom topography images, sidescan": "pb",
              "Sonar--bottom topography, near surface": "pc",
              "Sonar--bottom topography, near bottom": "pd",
              "Seismic surveys": "pe",
              "Other acoustical data": "pz",
              "Gravity anomalies (general)": "ra",
              "Free-air": "rb",
              "Bouger": "rc",
              "Isostatic": "rd",
              "Magnetic field": "sa",
              "radiometric surveys": "ta",
              "Unknown": "uu",
              "Other": "zz",
              "No attempt to code": "||"
            }
          ]
        },
        "$SOUND RECORDING": {
          "Specific material designation": [
            1,
            {
              "Sound disc": "d",
              "Cylinder": "e",
              "Sound cartridge": "g",
              "Sound-track film": "i",
              "Roll": "q",
              "Remote": "r",
              "Sound cassette": "s",
              "Sound-tape reel": "t",
              "Unspecified": "u",
              "Wire recording": "w",
              "Other": "z",
              "No attempt to code": "|"
            }
          ],
          "Speed": [
            3,
            {
              "16 rpm": "a",
              "33 1/3 rpm": "b",
              "45 rpm": "c",
              "78 rpm": "d",
              "8 rpm": "e",
              "1.4 m. per sec.": "f",
              "120 rpm": "h",
              "160 rpm": "i",
              "15/16 ips": "k",
              "1 7/8 ips": "l",
              "3 3/4 ips": "m",
              "Not applicable": "n",
              "7 1/2 ips": "o",
              "15 ips": "p",
              "30 ips": "r",
              "Unknown": "u",
              "Other": "z",
              "No attempt to code": "|"
            }
          ],
          "Configuration of playback channels": [
            4,
            {
              "Monaural": "m",
              "Quadraphonic, multichannel, or surround": "q",
              "Stereophonic": "s",
              "Unknown": "u",
              "Other": "z",
              "No attempt to code": "|"
            }
          ],
          "Groove width/groove pitch": [
            5,
            {
              "Microgroove/fine": "m",
              "Not applicable": "n",
              "Coarse/standard": "s",
              "Unknown": "u",
              "Other": "z",
              "No attempt to code": "|"
            }
          ],
          "Dimensions": [
            6,
            {
              "3 in.": "a",
              "5 in.": "b",
              "7 in.": "c",
              "10 in.": "d",
              "12 in.": "e",
              "16 in.": "f",
              "4 3/4 in. or 12 cm.": "g",
              "3 7/8 x 2 1/2 in.": "j",
              "5 1/4 x 3 7/8 in.": "o",
              "Not applicable": "n",
              "2 3/4 x 4 in.": "s",
              "Unknown": "u",
              "Other": "z",
              "No attempt to code": "|"
            }
          ],
          "Tape width": [
            7,
            {
              "1/8 in.": "l",
              "1/4 in.": "m",
              "Not applicable": "n",
              "1/2 in.": "o",
              "1 in.": "p",
              "Unknown": "u",
              "Other": "z",
              "No attempt to code": "|"
            }
          ],
          "Tape configuration": [
            8,
            {
              "Full (1) track": "a",
              "Half (2) track": "b",
              "Quarter (4) track": "c",
              "Eight track": "d",
              "Twelve track": "e",
              "Sixteen track": "f",
              "Not applicable": "n",
              "Unknown": "u",
              "Other": "z",
              "No attempt to code": "|"
            }
          ],
          "Kind of disc, cylinder or tape": [
            9,
            {
              "Master tape": "a",
              "Tape duplication master": "b",
              "Disc master (negative)": "d",
              "Instantaneous (recorded on the spot)": "i",
              "Mass produced": "m",
              "Not applicable": "n",
              "Mother (positive)": "r",
              "Stamper (negative)": "s",
              "Test pressing": "t",
              "Unknown": "u",
              "Other": "z",
              "No attempt to code": "|"
            }
          ],
          "Kind of material": [
            10,
            {
              "Lacquer coating": "a",
              "Cellulose nitrate": "b",
              "Acetate tape with ferrous oxide": "c",
              "Glass with lacquer": "g",
              "Aluminum with lacquer": "i",
              "Paper with lacquer or ferrous oxide": "r",
              "Metal": "l",
              "Plastic with metal": "m",
              "Not applicable": "n",
              "Plastic": "p",
              "Shellac": "s",
              "Unknown": "u",
              "Wax": "w",
              "Other": "z",
              "No attempt to code": "|"
            }
          ],
          "Kind of cutting": [
            11,
            {
              "Hill-and-dale cutting": "h",
              "Lateral or combined cutting": "l",
              "Not applicable": "n",
              "Unknown": "u",
              "No attempt to code": "|"
            }
          ],
          "Special playback characteristics": [
            12,
            {
              "NAB standard": "a",
              "CCIR standard": "b",
              "Dolby-B encoded": "c",
              "dbx encoded": "d",
              "Digital recording": "e",
              "Dolby-A encoded": "f",
              "Dolby-C encoded": "g",
              "CX encoded": "h",
              "Not applicable": "n",
              "Unknown": "u",
              "Other": "z",
              "No attempt to code": "|"
            }
          ],
          "Capture and storage technique": [
            13,
            {
              "Acoustical capture, direct storage": "a",
              "Direct storage, not acoustical": "b",
              "Digital storage": "d",
              "Analog electrical storage": "e",
              "Unknown": "u",
              "Other": "z",
              "No attempt to code": "|"
            }
          ]
        },
        "$TEXT": {
          "Specific material designation": [
            1,
            {
              "Videocartridge": "c",
              "Videodisc": "d",
              "Videocassette": "f",
              "Videoreel": "r",
              "Unspecified": "u",
              "Other": "z",
              "No attempt to code": "|"
            }
          ],
          "Color": [
            3,
            {
              "One color": "a",
              "Black-and-white": "b",
              "Multicolored": "c",
              "Mixed": "m",
              "Not applicable": "n",
              "Unknown": "u",
              "Other": "z",
              "No attempt to code": "|"
            }
          ],
          "Videorecording format": [
            4,
            {
              "Beta (1/2 in., videocassette)": "a",
              "VHS (1/2 in., videocassette)": "b",
              "U-matic (3/4 in., videocassette)": "c",
              "EIAJ (1/2 in. reel)": "d",
              "Type C (1 in., reel)": "e",
              "Quadruplex (1 in. or 2 in., reel)": "f",
              "Laserdisc": "g",
              "CED (Capacitance Electronic Disc) videodisc": "h",
              "Betacam (1/2 in., videocassette)": "i",
              "Betacam SP (1/2 in., videocassette)": "j",
              "Super-VHS (1/2 in., videocassette)": "k",
              "M-II (1/2 in., videocassette)": "m",
              "D-2 (3/4 in., videocassette)": "o",
              "8 mm.": "p",
              "Hi-8 mm.": "q",
              "Blu-ray disc": "s",
              "Unknown": "u",
              "DVD": "v",
              "Other": "z",
              "No attempt to code": "|"
            }
          ],
          "Sound on medium or separate": [
            5,
            {
              "No sound (silent)": "#",
              "Sound on medium": "a",
              "Sound separate from medium": "b",
              "Unknown": "u"
            }
          ],
          "Medium for sound": [
            6,
            {
              "No sound (silent)": "#",
              "Optical sound track on motion picture film": "a",
              "Magnetic sound track on motion picture film": "b",
              "Magnetic audio tape in cartridge": "c",
              "Sound disc": "d",
              "Magnetic audio tape on reel": "e",
              "Magnetic audio tape in cassette": "f",
              "Optical and magnetic sound track on motion picture film": "g",
              "Videotape": "h",
              "Videodisc": "i",
              "Unknown": "u",
              "Other": "z",
              "No attempt to code": "|"
            }
          ],
          "Dimensions": [
            7,
            {
              "8 mm.": "a",
              "1/4 in.": "m",
              "1/2 in.": "o",
              "1 in.": "p",
              "2 in.": "q",
              "3/4 in.": "r",
              "Unknown": "u",
              "Other": "z",
              "No attempt to code": "|"
            }
          ],
          "Configuration of playback channels": [
            8,
            {
              "Mixed": "k",
              "Monaural": "m",
              "Not applicable": "n",
              "Quadraphonic, multichannel, or surround": "q",
              "Stereophonic": "s",
              "Unknown": "u",
              "Other": "z",
              "No attempt to code": "|"
            }
          ]
        },
        "$UNSPECIFIED": {
          "Specific material designation": [
            1,
            {
              "Multiple physical forms": "m"
            }
          ]
        },
        "Mixed": "m",
        "Not applicable": "n",
        "Unknown": "u",
        "Unspecified": "u",
        "Other": "z",
        "No attempt to code": "|"
      }
    ],
    "DATA ELEMENTS": [
      "008",
      {
        "$ALL MATERIALS": {
          "Date entered on file": [
            0,
            5
          ],
          "Type of date/Publication status": [
            6,
            {
              "No dates given; B.C. date involved": "b",
              "Continuing resource currently published": "c",
              "Actual date and copyright date [OBSOLETE]": "c",
              "Continuing resource ceased publication": "d",
              "Detailed date [OBSOLETE]": "d",
              "Detailed date": "e",
              "Inclusive dates of collection": "i",
              "Range of years of bulk of collection": "k",
              "Multiple dates": "m",
              "Dates unknown": "n",
              "Date of distribution/release/issue and production/recording session when different": "p",
              "Questionable date": "q",
              "Reprint/reissue date and original date": "r",
              "Single known date/probable date": "s",
              "Publication date and copyright date": "t",
              "Continuing resource status unknown": "u",
              "No attempt to code": "|"
            }
          ],
          "Date 1": [
            7,
            10,
            {
              "Date digit": [
                1,
                9
              ],
              "Date element is not applicable": "#",
              "Date element is totally or partially unknown": "u",
              "No attempt to code": "|"
            }
          ],
          "Date 2": [
            11,
            14,
            {
              "Date digit": [
                1,
                9
              ],
              "Date element is not applicable": "#",
              "Date element is totally or partially unknown": "u",
              "No attempt to code": "|"
            }
          ],
          "Place of publication, production, or execution": [
            15,
            17
          ],
          "Language": [
            35,
            37
          ],
          "Modified record": [
            38,
            {
              "Not modified": "#",
              "Dashed-on information omitted": "d",
              "Completely romanized/printed cards romanized": "o",
              "Completely romanized/printed cards in script": "r",
              "Shortened": "s",
              "Missing characters": "x",
              "No attempt to code": "|"
            }
          ],
          "Cataloging source": [
            39,
            {
              "National bibliographic agency": "#",
              "National Agricultural Library [OBSOLETE]": "a",
              "National Library of Medicine [OBSOLETE]": "b",
              "Cooperative cataloging program": "c",
              "Other": "d",
              "Report to [OBSOLETE]": "n",
              "Unknown": "u",
              "No attempt to code": "|"
            }
          ]
        },
        "$Books": {
          "Illustrations": [
            18,
            21,
            {
              "No illustrations": "#",
              "Illustrations": "a",
              "Maps": "b",
              "Portraits": "c",
              "Charts": "d",
              "Plans": "e",
              "Plates": "f",
              "Music": "g",
              "Facsimiles": "h",
              "Coats of arms": "i",
              "Genealogical tables": "j",
              "Forms": "k",
              "Samples": "l",
              "Phonodisc, phonowire, etc.": "m",
              "Photographs": "o",
              "Illuminations": "p",
              "No attempt to code": "|"
            }
          ],
          "Target audience": [
            22,
            {
              "Unknown or not specified": "#",
              "Preschool": "a",
              "Primary": "b",
              "Pre-adolescent": "c",
              "Adolescent": "d",
              "Adult": "e",
              "Specialized": "f",
              "General": "g",
              "Juvenile": "j",
              "No attempt to code": "|"
            }
          ],
          "Form of item": [
            23,
            {
              "None of the following": "#",
              "Microfilm": "a",
              "Microfiche": "b",
              "Microopaque": "c",
              "Large print": "d",
              "Braille": "f",
              "Punched paper tape [OBSOLETE]": "g",
              "Magnetic tape [OBSOLETE]": "h",
              "Multimedia [OBSOLETE]": "i",
              "Online": "o",
              "Direct electronic": "q",
              "Regular print reproduction": "r",
              "Electronic": "s",
              "Other form of reproduction [OBSOLETE]": "z",
              "No attempt to code": "|"
            }
          ],
          "Nature of contents": [
            24,
            27,
            {
              "No specified nature of contents": "#",
              "Abstracts/summaries": "a",
              "Bibliographies": "b",
              "Catalogs": "c",
              "Dictionaries": "d",
              "Encyclopedias": "e",
              "Handbooks": "f",
              "Legal articles": "g",
              "Handbooks [OBSOLETE]": "h",
              "Indexes": "i",
              "Patent document": "j",
              "Discographies": "k",
              "Legislation": "l",
              "Theses": "m",
              "Surveys of literature in a subject area": "n",
              "Reviews": "o",
              "Programmed texts": "p",
              "Filmographies": "q",
              "Directories": "r",
              "Statistics": "s",
              "Technical reports": "t",
              "Standards/specifications": "u",
              "Legal cases and case notes": "v",
              "Law reports and digests": "w",
              "Technical reports [OBSOLETE]": "x",
              "Yearbooks": "y",
              "Treaties": "z",
              "Offprints": 2,
              "Calendars": 5,
              "Comics/graphic novels": 6,
              "No attempt to code": "|"
            }
          ],
          "Government publication": [
            28,
            {
              "Not a government publication": "#",
              "Autonomous or semi-autonomous component": "a",
              "Multilocal": "c",
              "Federal/national": "f",
              "International intergovernmental": "i",
              "Local": "l",
              "Multistate": "m",
              "Government publication--level undetermined [OBSOLETE]": "n",
              "Government publication--level undetermined": "o",
              "State, provincial, territorial, dependent, etc.": "s",
              "Unknown if item is government publication": "u",
              "Other": "z",
              "No attempt to code": "|"
            }
          ],
          "Conference publication": [
            29,
            {
              "Not a conference publication": 0,
              "Conference publication": 1,
              "No attempt to code": "|"
            }
          ],
          "Festschrift": [
            30,
            {
              "Not a festschrift": 0,
              "Festschrift": 1,
              "No attempt to code": "|"
            }
          ],
          "Index": [
            31,
            {
              "No index": 0,
              "Index present": 1,
              "No attempt to code": "|"
            }
          ],
          "Main entry in body of entry [OBSOLETE]": [
            32,
            {
              "Main entry not in body of entry": 0,
              "Main entry in body of entry": 1,
              "No attempt to code": "|"
            }
          ],
          "Literary form": [
            33,
            {
              "Not fiction (not further specified)": 0,
              "Fiction (not further specified)": 1,
              "Comic strips [OBSOLETE]": "c",
              "Dramas": "d",
              "Essays": "e",
              "Novels": "f",
              "Humor, satires, etc.": "h",
              "Letters": "i",
              "Short stories": "j",
              "Mixed forms": "m",
              "Poetry": "p",
              "Speeches": "s",
              "Unknown": "u",
              "No attempt to code": "|"
            }
          ],
          "Biography": [
            34,
            {
              "No biographical material": "#",
              "Autobiography": "a",
              "Individual biography": "b",
              "Collective biography": "c",
              "Contains biographical information": "d",
              "No attempt to code": "|"
            }
          ]
        },
        "$COMPUTER FILES": {
          "Frequency [OBSOLETE]": [
            18,
            {
              "No determinable frequency": "#",
              "Annual": "a",
              "Bimonthly": "b",
              "Semiweekly": "c",
              "Daily": "d",
              "Biweekly": "e",
              "Semiannual": "f",
              "Biennial": "g",
              "Triennial": "h",
              "Three times a week": "i",
              "Three times a month": "j",
              "Monthly": "m",
              "Not applicable": "n",
              "Quarterly": "q",
              "Semimonthly": "s",
              "Three times a year": "t",
              "Unknown": "u",
              "Weekly": "w",
              "Other frequencies": "z"
            }
          ],
          "Regularity [OBSOLETE]": [
            19,
            {
              "Not applicable": "#",
              "Normalized irregular": "n",
              "Regular": "r",
              "Unknown": "u",
              "Completely irregular": "x"
            }
          ],
          "Target audience": [
            22,
            {
              "Unknown or not specified": "#",
              "Preschool": "a",
              "Primary": "b",
              "Pre-adolescent": "c",
              "Adolescent": "d",
              "Adult": "e",
              "Specialized": "f",
              "General": "g",
              "Juvenile": "j",
              "No attempt to code": "|"
            }
          ],
          "Form of item": [
            23,
            {
              "Online": "o",
              "Direct electronic": "q"
            }
          ],
          "Type of computer file": [
            26,
            {
              "Numeric data": "a",
              "Computer program": "b",
              "Representational": "c",
              "Document": "d",
              "Bibliographic data": "e",
              "Font": "f",
              "Game": "g",
              "Sound": "h",
              "Interactive multimedia": "i",
              "Online system or service": "j",
              "Combination": "m",
              "Unknown": "u",
              "Other": "z",
              "No attempt to code": "|"
            }
          ],
          "Type of machine [OBSOLETE]": [
            27,
            {
              "Computer readable": "a",
              "Other": "z"
            }
          ],
          "Government publication": [
            28,
            {
              "Not a government publication": "#",
              "Autonomous or semi-autonomous component": "a",
              "Multilocal": "c",
              "Federal/national": "f",
              "International intergovernmental": "i",
              "Local": "l",
              "Multistate": "m",
              "Government publication--level undetermined": "o",
              "State, provincial, territorial, dependent, etc.": "s",
              "Unknown if item is government publication": "u",
              "Other": "z",
              "No attempt to code": "|"
            }
          ]
        },
        "$Maps": {
          "Relief": [
            18,
            21,
            {
              "No relief shown": "#",
              "Contours": "a",
              "Shading": "b",
              "Gradient and bathymetric tints": "c",
              "Hachures": "d",
              "Bathymetry/soundings": "e",
              "Form lines": "f",
              "Spot heights": "g",
              "Color [OBSOLETE]": "h",
              "Pictorially": "i",
              "Land forms": "j",
              "Bathymetry/isolines": "k",
              "Rock drawings": "m",
              "Other relief type": "z",
              "No attempt to code": "|"
            }
          ],
          "Projection": [
            22,
            23,
            {
              "Projection not specified": "##",
              "Aitoff": "aa",
              "Gnomic": "ab",
              "Lambert's azimuthal equal area": "ac",
              "Orthographic": "ad",
              "Azimuthal equidistant": "ae",
              "Stereographic": "af",
              "General vertical near-sided": "ag",
              "Modified stereographic for Alaska": "am",
              "Chamberlin trimetric": "an",
              "Polar stereographic": "ap",
              "Azimuthal, specific type unknown": "au",
              "Azimuthal, other": "az",
              "Gall": "ba",
              "Goode's homolographic": "bb",
              "Lambert's cylindrical equal area": "bc",
              "Mercator": "bd",
              "Miller": "be",
              "Mollweide": "bf",
              "Sinusoidal": "bg",
              "Transverse Mercator": "bh",
              "Gauss-Kruger": "bi",
              "Equirectangular": "bj",
              "Krovak": "bk",
              "Cassini-Soldner": "bl",
              "Oblique Mercator": "bo",
              "Robinson": "br",
              "Space oblique Mercator": "bs",
              "Cylindrical, specific type unknown": "bu",
              "Cylindrical, other": "bz",
              "Alber's equal area": "ca",
              "Bonne": "cb",
              "Lambert's conformal conic": "cc",
              "Equidistant conic": "ce",
              "Polyconic": "cp",
              "Conic, specific type unknown": "cu",
              "Conic, other": "cz",
              "Armadillo": "da",
              "Butterfly": "db",
              "Eckert": "dc",
              "Goode's homolosine": "dd",
              "Miller's bipolar oblique conformal conic": "de",
              "Van Der Grinten": "df",
              "Dimaxion": "dg",
              "Cordiform": "dh",
              "Lambert conformal": "dl",
              "Other": "zz",
              "No attempt to code": "|"
            }
          ],
          "Prime meridian [OBSOLETE]": [
            24,
            {
              "Prime meridian not specified": "#",
              "Greenwich": "e",
              "Ferro": "f",
              "Paris": "g",
              "Other [OBSOLETE]": "h",
              "Philadelphia": "p",
              "Washington, D.C.": "w",
              "Other": "z"
            }
          ],
          "Type of cartographic material": [
            25,
            {
              "Single map": "a",
              "Map series": "b",
              "Map serial": "c",
              "Globe": "d",
              "Atlas": "e",
              "Separate map supplement to another work": "f",
              "Map bound as part of another work": "g",
              "Unknown": "u",
              "Other": "z",
              "No attempt to code": "|"
            }
          ],
          "Publisher code [OBSOLETE]": [
            26,
            76
          ],
          "Government publication": [
            28,
            {
              "Not a government publication": "#",
              "Autonomous or semi-autonomous component": "a",
              "Multilocal": "c",
              "Federal/national": "f",
              "International intergovernmental": "i",
              "Local": "l",
              "Multistate": "m",
              "Government publication--level undetermined": "o",
              "State, provincial, territorial, dependent, etc.": "s",
              "Unknown if item is government publication": "u",
              "Other": "z",
              "No attempt to code": "|"
            }
          ],
          "Form of item": [
            29,
            {
              "None of the following": "#",
              "Microfilm": "a",
              "Microfiche": "b",
              "Microopaque": "c",
              "Large print": "d",
              "Braille": "f",
              "Online": "o",
              "Direct electronic": "q",
              "Regular print reproduction": "r",
              "Electronic": "s",
              "No attempt to code": "|"
            }
          ],
          "Index": [
            31,
            {
              "No index": 0,
              "Index present": 1,
              "No attempt to code": "|"
            }
          ],
          "Citation indicator [OBSOLETE]": 32,
          "Special format characteristics": [
            33,
            34,
            {
              "No specified special format characteristics": "#",
              "Photocopy, blue line print [OBSOLETE]": "a",
              "Photocopy [OBSOLETE]": "b",
              "Negative photocopy [OBSOLETE]": "c",
              "Film negative [OBSOLETE]": "d",
              "Manuscript": "e",
              "Facsimile [OBSOLETE]": "f",
              "Relief model [OBSOLETE]": "g",
              "Rare [OBSOLETE]": "h",
              "Picture card, post card": "j",
              "Calendar": "k",
              "Puzzle": "l",
              "Braille [OBSOLETE]": "m",
              "Game": "n",
              "Wall map": "o",
              "Playing cards": "p",
              "Large print [OBSOLETE]": "q",
              "Loose-leaf": "r",
              "Other": "z",
              "No attempt to code": "|"
            }
          ]
        },
        "$MUSIC": {
          "Form of composition": [
            18,
            19,
            {
              "Anthems": "an",
              "Ballads": "bd",
              "Bluegrass music": "bg",
              "Blues": "bl",
              "Ballets": "bt",
              "Chaconnes": "ca",
              "Chants, Other religions": "cb",
              "Chant, Christian": "cc",
              "Concerti grossi": "cg",
              "Chorales": "ch",
              "Chorale preludes": "cl",
              "Canons and rounds": "cn",
              "Concertos": "co",
              "Chansons, polyphonic": "cp",
              "Carols": "cr",
              "Chance compositions": "cs",
              "Cantatas": "ct",
              "Country music": "cy",
              "Canzonas": "cz",
              "Dance forms": "df",
              "Divertimentos, serenades, cassations, divertissements, notturni": "dv",
              "Fugues": "fg",
              "Flamenco": "fl",
              "Folk music": "fm",
              "Fantasias": "ft",
              "Gospel music": "gm",
              "Hymns": "hy",
              "Jazz": "jz",
              "Musical revues and comedies": "mc",
              "Madrigals": "md",
              "Minuets": "mi",
              "Motets": "mo",
              "Motion picture music": "mp",
              "Marches": "mr",
              "Masses": "ms",
              "Multiple forms": "mu",
              "Mazurkas": "mz",
              "Nocturnes": "nc",
              "Not applicable": "nn",
              "Operas": "op",
              "Oratorios": "or",
              "Overtures": "ov",
              "Program music": "pg",
              "Passion music": "pm",
              "Polonaises": "po",
              "Popular music": "pp",
              "Preludes": "pr",
              "Passacaglias": "ps",
              "Part-songs": "pt",
              "Pavans": "pv",
              "Rock music": "rc",
              "Rondos": "rd",
              "Ragtime music": "rg",
              "Ricercars": "ri",
              "Rhapsodies": "rp",
              "Requiems": "rq",
              "Square dance music": "sd",
              "Songs": "sg",
              "Sonatas": "sn",
              "Symphonic poems": "sp",
              "Studies and exercises": "st",
              "Suites": "su",
              "Symphonies": "sy",
              "Toccatas": "tc",
              "Teatro lirico": "tl",
              "Trio-sonatas": "ts",
              "Unknown": "uu",
              "Villancicos": "vi",
              "Variations": "vr",
              "Waltzes": "wz",
              "Zarzuelas": "za",
              "Other": "zz",
              "No attempt to code": "||"
            }
          ],
          "Format of music": [
            20,
            {
              "Full score": "a",
              "Miniature or study score": "b",
              "Accompaniment reduced for keyboard": "c",
              "Voice score with accompaniment omitted": "d",
              "Condensed score or piano-conductor score": "e",
              "Close score": "g",
              "Chorus score": "h",
              "Condensed score": "i",
              "Performer-conductor part": "j",
              "Vocal score": "k",
              "Score": "l",
              "Multiple score formats": "m",
              "Not applicable": "n",
              "Piano score": "p",
              "Unknown": "u",
              "Other": "z",
              "No attempt to code": "|"
            }
          ],
          "Music parts": [
            21,
            {
              "No parts in hand or not specified": "#",
              "Instrumental and vocal parts": "d",
              "Instrumental parts": "e",
              "Vocal parts": "f",
              "Not applicable": "n",
              "Unknown": "u",
              "No attempt to code": "|"
            }
          ],
          "Existence of parts [OBSOLETE]": [
            21,
            {
              "No parts exist": "#",
              "Parts exist": "a",
              "Not applicable": "n",
              "Unknown": "u"
            }
          ],
          "Target audience": [
            22,
            {
              "Unknown or not specified": "#",
              "Preschool": "a",
              "Primary": "b",
              "Pre-adolescent": "c",
              "Adolescent": "d",
              "Adult": "e",
              "Specialized": "f",
              "General": "g",
              "Juvenile": "j",
              "No attempt to code": "|"
            }
          ],
          "Form of item": [
            23,
            {
              "None of the following": "#",
              "Microfilm": "a",
              "Microfiche": "b",
              "Microopaque": "c",
              "Large print": "d",
              "Braille": "f",
              "Punched paper tape [   ]": "g",
              "Magnetic tape [OBSOLETE]": "h",
              "Multimedia [OBSOLETE]": "i",
              "Online": "o",
              "Direct electronic": "q",
              "Regular print reproduction": "r",
              "Electronic": "s",
              "Other form of reproduction [OBSOLETE]": "z",
              "No attempt to code": "|"
            }
          ],
          "Accompanying matter": [
            24,
            29,
            {
              "No accompanying matter": "#",
              "Discography": "a",
              "Bibliography": "b",
              "Thematic index": "c",
              "Libretto or text": "d",
              "Biography of composer or author": "e",
              "Biography of performer or history of ensemble": "f",
              "Technical and/or historical information on instruments": "g",
              "Technical information on music": "h",
              "Historical information": "i",
              "Historical information other than music [OBSOLETE]": "j",
              "Ethnological information": "k",
              "Not applicable [OBSOLETE]": "n",
              "Instructional materials": "r",
              "Music": "s",
              "Other": "z",
              "No attempt to code": "|"
            }
          ],
          "Literary text for sound recordings": [
            30,
            31,
            {
              "Item is a musical sound recording": "#",
              "Autobiography": "a",
              "Biography": "b",
              "Conference proceedings": "c",
              "Drama": "d",
              "Essays": "e",
              "Fiction": "f",
              "Reporting": "g",
              "History": "h",
              "Instruction": "i",
              "Language instruction": "j",
              "Comedy": "k",
              "Lectures, speeches": "l",
              "Memoirs": "m",
              "Not applicable": "n",
              "Folktales": "o",
              "Poetry": "p",
              "Rehearsals": "r",
              "Sounds": "s",
              "Interviews": "t",
              "Other": "z",
              "No attempt to code": "|"
            }
          ],
          "Main entry in body of entry [OBSOLETE]": [
            32,
            {
              "Main entry not in body of entry": 0,
              "Main entry in body of entry": 1,
              "No attempt to code": "|"
            }
          ],
          "Transposition and arrangement": [
            33,
            {
              "Not arrangement or transposition or not specified": "#",
              "Transposition": "a",
              "Arrangement": "b",
              "Both transposed and arranged": "c",
              "Not applicable": "n",
              "Unknown": "u",
              "No attempt to code": "|"
            }
          ]
        },
        "$CONTINUING RESOURCES": {
          "Frequency": [
            18,
            {
              "No determinable frequency": "#",
              "Annual": "a",
              "Bimonthly": "b",
              "Semiweekly": "c",
              "Daily": "d",
              "Biweekly": "e",
              "Semiannual": "f",
              "Biennial": "g",
              "Triennial": "h",
              "Three times a week": "i",
              "Three times a month": "j",
              "Continuously updated": "k",
              "Monthly": "m",
              "Quarterly": "q",
              "Semimonthly": "s",
              "Three times a year": "t",
              "Unknown": "u",
              "Weekly": "w",
              "Other": "z",
              "No attempt to code": "|"
            }
          ],
          "Regularity": [
            19,
            {
              "Normalized irregular": "n",
              "Regular": "r",
              "Unknown": "u",
              "Completely irregular": "x",
              "No attempt to code": "|"
            }
          ],
          "ISSN center [OBSOLETE]": [
            20,
            {
              "No ISSN center code assigned": "#",
              "International Center": 0,
              "United States": 1,
              "United Kingdom": 2,
              "Australia [OBSOLETE]": 3,
              "Canada": 4,
              "Moscow Regional Centre [OBSOLETE]": 5,
              "Federal Republic of Germany [OBSOLETE]": 6,
              "France [OBSOLETE]": 7,
              "Argentina [OBSOLETE]": 8,
              "Japan [OBSOLETE]": 9,
              "Unknown [OBSOLETE]": "u",
              "Other": "z",
              "No attempt to code": "|"
            }
          ],
          "Type of continuing resource": [
            21,
            {
              "None of the following": "#",
              "Updating database": "d",
              "Updating loose-leaf": "l",
              "Monographic series": "m",
              "Newspaper": "n",
              "Periodical": "p",
              "Updating Web site": "w",
              "No attempt to code": "|"
            }
          ],
          "Form of original item": [
            22,
            {
              "None of the following": "#",
              "Microfilm": "a",
              "Microfiche": "b",
              "Microopaque": "c",
              "Large print": "d",
              "Newspaper format": "e",
              "Braille": "f",
              "Punched paper tape [OBSOLETE]": "g",
              "Magnetic tape [OBSOLETE]": "h",
              "Multimedia [OBSOLETE]": "i",
              "Online": "o",
              "Direct electronic": "q",
              "Electronic": "s",
              "Other physical medium [OBSOLETE]": "z",
              "No attempt to code": "|"
            }
          ],
          "Form of item": [
            23,
            {
              "None of the following": "#",
              "Microfilm": "a",
              "Microfiche": "b",
              "Microopaque": "c",
              "Large print": "d",
              "Braille": "f",
              "Punched paper tape [OBSOLETE]": "g",
              "Magnetic tape [OBSOLETE]": "h",
              "Multimedia [OBSOLETE]": "i",
              "Online": "o",
              "Direct electronic": "q",
              "Regular print reproduction": "r",
              "Electronic": "s",
              "Other form of reproduction [OBSOLETE]": "z",
              "No attempt to code": "|"
            }
          ],
          "Nature of entire work": [
            24,
            {
              "No specified nature of entire work": "#",
              "Abstracts/summaries": "a",
              "Bibliographies": "b",
              "Catalogs": "c",
              "Dictionaries": "d",
              "Encyclopedias": "e",
              "Handbooks": "f",
              "Legal articles": "g",
              "Biography": "h",
              "Indexes": "i",
              "Discographies": "k",
              "Legislation": "l",
              "Theses": "m",
              "Surveys of literature in a subject area": "n",
              "Legal cases and case notes [OBSOLETE]": "n",
              "Reviews": "o",
              "Programmed texts": "p",
              "Filmographies": "q",
              "Directories": "r",
              "Statistics": "s",
              "Technical reports": "t",
              "Standards/specifications": "u",
              "Legal cases and case notes": "v",
              "Law reports and digests": "w",
              "Yearbooks": "y",
              "Treaties": "z",
              "Calendars": 5,
              "Comics/graphic novels": 6,
              "No attempt to code": "|"
            }
          ],
          "Nature of contents": [
            25,
            27,
            {
              "No specified nature of contents": "#",
              "Abstracts/summaries": "a",
              "Bibliographies": "b",
              "Catalogs": "c",
              "Dictionaries": "d",
              "Encyclopedias": "e",
              "Handbooks": "f",
              "Legal articles": "g",
              "Biography": "h",
              "Indexes": "i",
              "Discographies": "k",
              "Legislation": "l",
              "Theses": "m",
              "Surveys of literature in a subject area": "n",
              "Legal cases and case notes [OBSOLETE]": "n",
              "Reviews": "o",
              "Programmed texts": "p",
              "Filmographies": "q",
              "Directories": "r",
              "Statistics": "s",
              "Technical reports": "t",
              "Standards/specifications": "u",
              "Legal cases and case notes": "v",
              "Law reports and digests": "w",
              "Yearbooks": "y",
              "Treaties": "z",
              "Calendars": 5,
              "Comics/graphic novels": 6,
              "No attempt to code": "|"
            }
          ],
          "Government publication": [
            28,
            {
              "Not a government publication": "#",
              "Autonomous or semi-autonomous component": "a",
              "Multilocal": "c",
              "Federal/national": "f",
              "International intergovernmental": "i",
              "Local": "l",
              "Multistate": "m",
              "Government publication--level undetermined [OBSOLETE]": "n",
              "Government publication--level undetermined": "o",
              "State, provincial, territorial, dependent,etc.": "s",
              "Unknown if item is government publication": "u",
              "Other": "z",
              "No attempt to code": "|"
            }
          ],
          "Conference publication": [
            29,
            {
              "Not a conference publication": 0,
              "Conference publication": 1,
              "No attempt to code": "|"
            }
          ],
          "Title page availability [OBSOLETE]": [
            30,
            {
              "No separate title page issued": "#",
              "In last issue of volume, loose": "a",
              "In last issue of volume, attached": "b",
              "In first issue of next volume, loose": "c",
              "In first issue of next volume, attached": "d",
              "Published separately, free upon request": "e",
              "Published separately, free, automatically sent": "f",
              "Published separately, purchase, request": "g",
              "Unknown": "u",
              "Other title page availability": "z",
              "No attempt to code": "|"
            }
          ],
          "Index availability [OBSOLETE]": [
            31,
            {
              "No index published": "#",
              "Each issue contains index to its own contents (no volume index), loose": "a",
              "In last issue of volume, loose, separately paged": "b",
              "In last issue of volume, loose, unpaged": "c",
              "In last issue of volume, attached": "d",
              "In first issue of next volume, loose, separately paged": "e",
              "In first issue of next volume, loose, unpaged": "f",
              "In first issue of next volume, attached": "g",
              "Published separately, free, automatically sent": "h",
              "Published separately, free, upon request": "i",
              "Published separately, bound from publisher, free, automatically sent": "j",
              "Published separately, bound from publisher, free, upon request": "k",
              "Received separately, bound from publisher": "l",
              "Supplement or subseries, indexed in parent journal index": "m",
              "Unknown": "u",
              "Other index availability": "z",
              "No attempt to code": "|"
            }
          ],
          "Cumulative index availability [OBSOLETE]": [
            32,
            {
              "No cumulative index available": 0,
              "Cumulative index available": 1,
              "Unknown": "u",
              "No attempt to code": "|"
            }
          ],
          "Original alphabet or script of title": [
            33,
            {
              "No alphabet or script given/no key title": "#",
              "Basic roman": "a",
              "Extended roman": "b",
              "Cyrillic": "c",
              "Japanese": "d",
              "Chinese": "e",
              "Arabic": "f",
              "Greek": "g",
              "Hebrew": "h",
              "Thai": "i",
              "Devanagari": "j",
              "Korean": "k",
              "Tamil": "l",
              "Unknown": "u",
              "Other": "z",
              "No attempt to code": "|"
            }
          ],
          "Entry convention": [
            34,
            {
              "Successive entry": 0,
              "Latest entry": 1,
              "Integrated entry": 2,
              "No attempt to code": "|"
            }
          ]
        },
        "$VISUAL MATERIALS": {
          "Running time for motion pictures and videorecordings": [
            18,
            20,
            {
              "Running time exceeds three characters": 0,
              "Running time": [
                1,
                999
              ],
              "Running time unknown": "---",
              "Not applicable": "nnn",
              "No attempt to code": "|||"
            }
          ],
          "In LC collection [OBSOLETE]": [
            21,
            {
              "Not in LC": "#",
              "In LC, print note": "a",
              "In LC, do not print note": "b",
              "Unknown": "u"
            }
          ],
          "Target audience": [
            22,
            {
              "Unknown or not specified": "#",
              "Preschool": "a",
              "Primary": "b",
              "Pre-adolescent": "c",
              "Adolescent": "d",
              "Adult": "e",
              "Specialized": "f",
              "General": "g",
              "Juvenile": "j",
              "No attempt to code": "|"
            }
          ],
          "Accompanying matter [OBSOLETE]": [
            23,
            27,
            {
              "No accompanying matter": "#",
              "No [OBSOLETE]": 0,
              "Yes [OBSOLETE]": 1,
              "Stills": "l",
              "Script material": "m",
              "Posters": "o",
              "Pressbooks": "p",
              "Lobby cards": "q",
              "Instructional materials": "r",
              "Music": "s",
              "Other": "z",
              "No attempt to code": "|"
            }
          ],
          "Government publication": [
            28,
            {
              "Not a government publication": "#",
              "Autonomous or semi-autonomous component": "a",
              "Multilocal": "c",
              "Federal/national": "f",
              "International intergovernmental": "i",
              "Local": "l",
              "Multistate": "m",
              "Government publication--level undetermined [OBSOLETE]": "n",
              "Government publication--level undetermined": "o",
              "State, provincial, territorial, dependent, etc.": "s",
              "Unknown if item is government publication": "u",
              "Other": "z",
              "No attempt to code": "|"
            }
          ],
          "Form of item": [
            29,
            {
              "None of the following": "#",
              "Microfilm": "a",
              "Microfiche": "b",
              "Microopaque": "c",
              "Large print": "d",
              "Braille": "f",
              "Online": "o",
              "Direct electronic": "q",
              "Regular print reproduction": "r",
              "Electronic": "s",
              "No attempt to code": "|"
            }
          ],
          "Main entry in body of entry [OBSOLETE]": [
            32,
            {
              "Main entry not in body of entry": 0,
              "Main entry in body of entry": 1,
              "No attempt to code": "|"
            }
          ],
          "Type of visual material": [
            33,
            {
              "Art original": "a",
              "Kit": "b",
              "Art reproduction": "c",
              "Diorama": "d",
              "Electronic videorecording [OBSOLETE]": "e",
              "Filmstrip": "f",
              "Game": "g",
              "Picture": "i",
              "Graphic": "k",
              "Technical drawing": "l",
              "Motion picture": "m",
              "Chart": "n",
              "Flash card": "o",
              "Microscope slide": "p",
              "Model": "q",
              "Realia": "r",
              "Slide": "s",
              "Transparency": "t",
              "Videorecording": "v",
              "Toy": "w",
              "Other": "z",
              "No attempt to code": "|"
            }
          ],
          "Technique": [
            34,
            {
              "Not applicable [OBSOLETE]": "#",
              "Animation": "a",
              "Animation and live action": "c",
              "Live action": "l",
              "Not applicable": "n",
              "Unknown": "u",
              "Other technique": "z",
              "No attempt to code": "|"
            }
          ]
        },
        "$MIXED MATERIALS": {
          "Form of item": [
            23,
            {
              "None of the following": "#",
              "Microfilm": "a",
              "Microfiche": "b",
              "Microopaque": "c",
              "Large print": "d",
              "Braille": "f",
              "Punched paper tape [OBSOLETE]": "g",
              "Magnetic tape [OBSOLETE]": "h",
              "Multimedia [OBSOLETE]": "i",
              "Handwritten transcript [OBSOLETE]": "j",
              "Online": "o",
              "Photocopy [OBSOLETE]": "p",
              "Direct electronic": "q",
              "Regular print reproduction": "r",
              "Electronic": "s",
              "Typewritten transcript [OBSOLETE]": "t",
              "Other form of reproduction [OBSOLETE]": "z",
              "No attempt to code": "|"
            }
          ],
          "Case file indicator [OBSOLETE]": [
            30,
            {
              "No case file exists": "#",
              "Case file exists": "c"
            }
          ],
          "Processing status code [OBSOLETE]": [
            32,
            {
              "Collection not in library": "a",
              "Completely processed": "b",
              "Processed but with unprocessed additions": "c",
              "Requires processing": "d",
              "Totally unprocessed": "e",
              "Under total cloture": "f",
              "Unknown": "u"
            }
          ],
          "Collection status code [OBSOLETE]": [
            33,
            {
              "Discrete grouping of material": "a",
              "Accession": "b",
              "Active solicitation": "c",
              "Solicitation unsuccessful": "d",
              "Information file only": "e",
              "Unknown": "u"
            }
          ],
          "Level of collection control code [OBSOLETE]": [
            34,
            {
              "Control on collection level": "a",
              "Control by series": "b",
              "Control by container": "c",
              "Control by folder": "d",
              "Control by item": "e",
              "Unknown": "u"
            }
          ]
        }
      }
    ],
    "PHYSICAL DESCRIPTION FIXED-FIELD FOR ARCHIVAL COLLECTION (VM) - [OBSOLETE]": [
      "009",
      {
        "Genealogical stage": 0,
        "Technical stage": 1,
        "Color stage": 2,
        "Film emulsion": 3,
        "Film base": 4,
        "Negative or positive sound": 5,
        "Additional types of color": 6,
        "Longitudinal shrinkage": 7,
        "Perforation shrinkage": 8,
        "Film deterioration": 9,
        "Completeness": 10,
        "Film inspection date": [11,14]
      }
    ]
  },
  "datafield": {
    "Title Statement": [
      "245",
      {
        "Title": "{a}",
        "Remainder of title": "{b}",
        "Statement of responsibility, etc": "{c}",
        "Designation of section": "{d}",
        "Name of part/section": "{e}",
        "Inclusive dates": "{f}",
        "Bulk dates": "{g}",
        "Medium": "{h}",
        "Form": "{k}",
        "Number of part/section of a work": "{n}",
        "Name of part/section of a work": "{p}",
        "Version": "{s}",
        "Linkage": "{6}",
        "Field link and sequence number": "{8}"
      }
    ]
  }
}